gupta_flowshop/__init__.py
gupta_flowshop/gupta_heuristic.py
gupta_flowshop_optimizer-0.1.1.dist-info/METADATA
gupta_flowshop_optimizer-0.1.1.dist-info/WHEEL
gupta_flowshop_optimizer-0.1.1.dist-info/entry_points.txt
gupta_flowshop_optimizer-0.1.1.dist-info/top_level.txt
gupta_flowshop_optimizer-0.1.1.dist-info/RECORD
